Metadata-Version: 2.1
Name: flet-pb-v-calc
Version: 1.0
Summary: Flet Progress Bar Value Calculator.
Home-page: https://github.com/xzripper/flet_pb_v_calc
Author: Ivan Perzhinsky.
Author-email: name1not1found.com@gmail.com
License: MIT
Download-URL: https://github.com/xzripper/flet_pb_v_calc/archive/refs/tags/v1.0.tar.gz
Keywords: utility
Platform: UNKNOWN
Classifier: Development Status :: 5 - Production/Stable
Classifier: Intended Audience :: Developers
Classifier: Topic :: Utilities
Classifier: License :: OSI Approved :: MIT License
Classifier: Programming Language :: Python :: 3
License-File: LICENSE.txt
